petrelic.libs/libgmp-f8de2039.so.10.4.0
petrelic.libs/librelic-18280b12.so
petrelic-0.1.4.data/data/LICENSE.LGPL-2.1
petrelic-0.1.4.data/data/LICENSE.RELIC
petrelic-0.1.4.data/data/LICENSE
petrelic-0.1.4.data/data/LICENSE.LGPLv3
petrelic-0.1.4.data/data/LICENSE.GPLv2
petrelic-0.1.4.data/data/LICENSE.GMP
petrelic-0.1.4.data/data/LICENSE.Apache-2.0
petrelic/bindings.py
petrelic/constants.py
petrelic/compile.py
petrelic/bn.py
petrelic/_petrelic.abi3.so
petrelic/__init__.py
petrelic/additive/pairing.py
petrelic/additive/__init__.py
petrelic/petlib/pairing.py
petrelic/petlib/__init__.py
petrelic/native/pairing.py
petrelic/native/__init__.py
petrelic/multiplicative/pairing.py
petrelic/multiplicative/__init__.py
petrelic-0.1.4.dist-info/top_level.txt
petrelic-0.1.4.dist-info/WHEEL
petrelic-0.1.4.dist-info/RECORD
petrelic-0.1.4.dist-info/METADATA
